matplotlib_polyroi/__init__.py
matplotlib_polyroi/funcs.py
matplotlib_polyroi/roi.py
matplotlib_polyroi-0.1.8.dist-info/LICENSE
matplotlib_polyroi-0.1.8.dist-info/METADATA
matplotlib_polyroi-0.1.8.dist-info/WHEEL
matplotlib_polyroi-0.1.8.dist-info/top_level.txt
matplotlib_polyroi-0.1.8.dist-info/RECORD
