Metadata-Version: 2.1
Name: matplotlib-polyroi
Version: 0.1.8
Summary: Module for selecting polygonal ROIs on images, spline fitting and ROI expansion
Author-email: Tom Bland <tom_bland@hotmail.co.uk>
License: Attribution 4.0 International
Project-URL: Documentation, https://matplotlib-polyroi.readthedocs.io/
Project-URL: Source, https://github.com/tsmbland/matplotlib-polyroi
License-File: LICENSE
Requires-Dist: numpy
Requires-Dist: matplotlib
Requires-Dist: scipy
Requires-Dist: scikit-image
Requires-Dist: ipympl
Provides-Extra: dev
Requires-Dist: pre-commit ; extra == 'dev'
Requires-Dist: black ; extra == 'dev'
Requires-Dist: pip-tools ; extra == 'dev'
Provides-Extra: doc
Requires-Dist: sphinx-rtd-theme ==1.0.0 ; extra == 'doc'
